{
  "generatedAt": "2026-06-03T20:05:32.958979",
  "refreshInterval": "1h",
  "nextRefresh": "整点自动刷新",
  "boards": {
    "discussionSprouts": [
      {
        "id": "ds1",
        "title": "TI2026门票6月10日发售，优先购抢先购票！",
        "game": "DOTA2",
        "board": "discussion",
        "signalType": "讨论苗头",
        "commentToLikeRatio": 0.71,
        "commentCount": 326,
        "likeCount": 460,
        "tgi": "均衡",
        "sourceNoteUrl": "https://www.xiaohongshu.com/explore/6a151edb000000003601e350",
        "topComments": [],
        "sampleNotes": [],
        "noteCount": 1,
        "analysis": "社区热点讨论 · 讨论质量较高（评赞比0.71），评论区活跃度明显超过内容本身",
        "suggestion": "围绕\"TI2026门票6月10日发售，优先购抢\"创作相关内容 · 讨论活跃(评论326) — 建议在话题热度消退前完成内容准备",
        "generatedAt": "2026-06-03T20:05:32.958798"
      },
      {
        "id": "ds2",
        "title": "26年第12周TOP100手游流水排行!大盘止跌！",
        "game": "穿越火线：枪战王者",
        "board": "discussion",
        "signalType": "讨论苗头",
        "commentToLikeRatio": 0.42,
        "commentCount": 97,
        "likeCount": 229,
        "tgi": "均衡",
        "sourceNoteUrl": "https://www.xiaohongshu.com/explore/69c14ba100000000230276f7",
        "topComments": [],
        "sampleNotes": [],
        "noteCount": 1,
        "analysis": "排行/对比话题讨论 · 讨论质量中等偏上（评赞比0.42），潜在讨论信号",
        "suggestion": "围绕\"26年第12周TOP100手游流水排行!\"创作相关内容 · 讨论活跃(评论97) — 建议在话题热度消退前完成内容准备",
        "generatedAt": "2026-06-03T20:05:32.958824"
      },
      {
        "id": "ds3",
        "title": "比得过零氪最强轻狙M200-幻神吗？",
        "game": "穿越火线：枪战王者",
        "board": "discussion",
        "signalType": "讨论苗头",
        "commentToLikeRatio": 0.42,
        "commentCount": 95,
        "likeCount": 227,
        "tgi": "均衡",
        "sourceNoteUrl": "https://www.xiaohongshu.com/explore/69922233000000000c035c90",
        "topComments": [],
        "sampleNotes": [],
        "noteCount": 1,
        "analysis": "排行/对比话题讨论 · 讨论质量中等偏上（评赞比0.42），潜在讨论信号",
        "suggestion": "围绕\"比得过零氪最强轻狙M200-幻神吗？\"创作相关内容 · 讨论活跃(评论95) — 建议在话题热度消退前完成内容准备",
        "generatedAt": "2026-06-03T20:05:32.958835"
      },
      {
        "id": "ds4",
        "title": "第一人称射击游戏排行榜前十名",
        "game": "穿越火线：枪战王者",
        "board": "discussion",
        "signalType": "讨论苗头",
        "commentToLikeRatio": 0.36,
        "commentCount": 378,
        "likeCount": 1041,
        "tgi": "男性向",
        "sourceNoteUrl": "https://www.xiaohongshu.com/explore/69c1209e00000000210061c6",
        "topComments": [],
        "sampleNotes": [],
        "noteCount": 1,
        "analysis": "排行/对比话题讨论 · 讨论质量中等偏上（评赞比0.36），潜在讨论信号",
        "suggestion": "围绕\"第一人称射击游戏排行榜前十名\"创作相关内容 · 讨论活跃(评论378) — 建议在话题热度消退前完成内容准备",
        "generatedAt": "2026-06-03T20:05:32.958844"
      },
      {
        "id": "ds5",
        "title": "前T1教练Roach：23年打JDG最难，珉炯吃太多苦",
        "game": "英雄联盟",
        "board": "discussion",
        "signalType": "讨论苗头",
        "commentToLikeRatio": 0.34,
        "commentCount": 123,
        "likeCount": 357,
        "tgi": "均衡",
        "sourceNoteUrl": "https://www.xiaohongshu.com/explore/6a1f910e00000000220234c1",
        "topComments": [],
        "sampleNotes": [],
        "noteCount": 1,
        "analysis": "社区热点讨论 · 讨论质量中等偏上（评赞比0.34），潜在讨论信号",
        "suggestion": "围绕\"前T1教练Roach：23年打JDG最难\"创作相关内容 · 讨论活跃(评论123) — 建议在话题热度消退前完成内容准备",
        "generatedAt": "2026-06-03T20:05:32.958855"
      },
      {
        "id": "ds6",
        "title": "上海TI直邀公告",
        "game": "DOTA2",
        "board": "discussion",
        "signalType": "讨论苗头",
        "commentToLikeRatio": 0.33,
        "commentCount": 232,
        "likeCount": 696,
        "tgi": "均衡",
        "sourceNoteUrl": "https://www.xiaohongshu.com/explore/6a15306b0000000038020604",
        "topComments": [],
        "sampleNotes": [],
        "noteCount": 1,
        "analysis": "版本更新讨论 · 讨论质量中等偏上（评赞比0.33），潜在讨论信号",
        "suggestion": "围绕\"上海TI直邀公告\"创作相关内容 · 讨论活跃(评论232) — 建议在话题热度消退前完成内容准备",
        "generatedAt": "2026-06-03T20:05:32.958864"
      },
      {
        "id": "ds7",
        "title": "拍成这样能在北京找互勉么",
        "game": "DOTA2",
        "board": "discussion",
        "signalType": "讨论苗头",
        "commentToLikeRatio": 0.28,
        "commentCount": 70,
        "likeCount": 249,
        "tgi": "女性向",
        "sourceNoteUrl": "https://www.xiaohongshu.com/explore/6a06f1940000000036001d81",
        "topComments": [],
        "sampleNotes": [],
        "noteCount": 1,
        "analysis": "社区热点讨论 · 讨论质量中等（评赞比0.28），讨论正在发酵初期",
        "suggestion": "围绕\"拍成这样能在北京找互勉么\"创作相关内容 · 讨论活跃(评论70) — 建议在话题热度消退前完成内容准备",
        "generatedAt": "2026-06-03T20:05:32.958873"
      },
      {
        "id": "ds8",
        "title": "donk和ame跨界合影",
        "game": "DOTA2",
        "board": "discussion",
        "signalType": "讨论苗头",
        "commentToLikeRatio": 0.24,
        "commentCount": 64,
        "likeCount": 272,
        "tgi": "均衡",
        "sourceNoteUrl": "https://www.xiaohongshu.com/explore/6a14b89e000000003501dcea",
        "topComments": [],
        "sampleNotes": [],
        "noteCount": 1,
        "analysis": "社区热点讨论 · 讨论质量中等（评赞比0.24），讨论正在发酵初期",
        "suggestion": "围绕\"donk和ame跨界合影\"创作相关内容 · 讨论活跃(评论64) — 建议在话题热度消退前完成内容准备",
        "generatedAt": "2026-06-03T20:05:32.958888"
      },
      {
        "id": "ds9",
        "title": "吃鸡秘诀！6月3日最新上分阵容推荐榜单",
        "game": "金铲铲之战",
        "board": "discussion",
        "signalType": "讨论苗头",
        "commentToLikeRatio": 0.21,
        "commentCount": 89,
        "likeCount": 414,
        "tgi": "男性向",
        "sourceNoteUrl": "https://www.xiaohongshu.com/explore/6a1f88c9000000003603357e",
        "topComments": [],
        "sampleNotes": [],
        "noteCount": 1,
        "analysis": "版本更新讨论 · 讨论质量中等（评赞比0.21），讨论正在发酵初期",
        "suggestion": "围绕\"吃鸡秘诀！6月3日最新上分阵容推荐榜单\"创作相关内容 · 讨论活跃(评论89) — 建议在话题热度消退前完成内容准备",
        "generatedAt": "2026-06-03T20:05:32.958898"
      },
      {
        "id": "ds10",
        "title": "为什么说在暗区六套面前",
        "game": "暗区突围",
        "board": "discussion",
        "signalType": "讨论苗头",
        "commentToLikeRatio": 0.2,
        "commentCount": 80,
        "likeCount": 405,
        "tgi": "均衡",
        "sourceNoteUrl": "https://www.xiaohongshu.com/explore/6a1efc1e000000002200a9f7",
        "topComments": [],
        "sampleNotes": [],
        "noteCount": 1,
        "analysis": "社区热点讨论 · 讨论质量中等（评赞比0.2），讨论正在发酵初期",
        "suggestion": "围绕\"为什么说在暗区六套面前\"创作相关内容 · 讨论活跃(评论80) — 建议在话题热度消退前完成内容准备",
        "generatedAt": "2026-06-03T20:05:32.958906"
      },
      {
        "id": "ds11",
        "title": "夺舍刘涛+ASval+M7+AWM，1107万撤离！",
        "game": "三角洲行动",
        "board": "discussion",
        "signalType": "讨论苗头",
        "commentToLikeRatio": 0.19,
        "commentCount": 70,
        "likeCount": 374,
        "tgi": "均衡",
        "sourceNoteUrl": "https://www.xiaohongshu.com/explore/6a200fec0000000022027f8c",
        "topComments": [],
        "sampleNotes": [],
        "noteCount": 1,
        "analysis": "社区热点讨论 · 讨论质量中等（评赞比0.19），讨论正在发酵初期",
        "suggestion": "围绕\"夺舍刘涛+ASval+M7+AWM，11\"创作相关内容 · 讨论活跃(评论70) — 建议在话题热度消退前完成内容准备",
        "generatedAt": "2026-06-03T20:05:32.958915"
      },
      {
        "id": "ds12",
        "title": "全球首场DOTA2交响音乐会即将奏响",
        "game": "DOTA2",
        "board": "discussion",
        "signalType": "讨论苗头",
        "commentToLikeRatio": 0.19,
        "commentCount": 55,
        "likeCount": 295,
        "tgi": "均衡",
        "sourceNoteUrl": "https://www.xiaohongshu.com/explore/6a17ef180000000035020e50",
        "topComments": [],
        "sampleNotes": [],
        "noteCount": 1,
        "analysis": "社区热点讨论 · 讨论质量中等（评赞比0.19），讨论正在发酵初期",
        "suggestion": "围绕\"全球首场DOTA2交响音乐会即将奏响\"创作相关内容 · 讨论活跃(评论55) — 建议在话题热度消退前完成内容准备",
        "generatedAt": "2026-06-03T20:05:32.958923"
      },
      {
        "id": "ds13",
        "title": "飞天走地双龙王丨管你天上地下我都要管",
        "game": "金铲铲之战",
        "board": "discussion",
        "signalType": "讨论苗头",
        "commentToLikeRatio": 0.16,
        "commentCount": 33,
        "likeCount": 209,
        "tgi": "男性向",
        "sourceNoteUrl": "https://www.xiaohongshu.com/explore/6a1fa2eb000000003700ddf6",
        "topComments": [],
        "sampleNotes": [],
        "noteCount": 1,
        "analysis": "社区热点讨论 · 讨论质量中等（评赞比0.16），讨论正在发酵初期",
        "suggestion": "围绕\"飞天走地双龙王丨管你天上地下我都要管\"创作相关内容 · 讨论活跃(评论33) — 建议在话题热度消退前完成内容准备",
        "generatedAt": "2026-06-03T20:05:32.958931"
      },
      {
        "id": "ds14",
        "title": "地铁真正的猛攻《苏尔南狮子星》",
        "game": "和平精英",
        "board": "discussion",
        "signalType": "讨论苗头",
        "commentToLikeRatio": 0.15,
        "commentCount": 31,
        "likeCount": 213,
        "tgi": "均衡",
        "sourceNoteUrl": "https://www.xiaohongshu.com/explore/6a1ebcf5000000003701cac5",
        "topComments": [],
        "sampleNotes": [],
        "noteCount": 1,
        "analysis": "社区热点讨论 · 讨论质量轻度（评赞比0.15），轻度讨论信号",
        "suggestion": "围绕\"地铁真正的猛攻《苏尔南狮子星》\"创作相关内容 · 讨论活跃(评论31) — 建议在话题热度消退前完成内容准备",
        "generatedAt": "2026-06-03T20:05:32.958940"
      },
      {
        "id": "ds15",
        "title": "《女坦薇古丝95》稳上分攻略",
        "game": "金铲铲之战",
        "board": "discussion",
        "signalType": "讨论苗头",
        "commentToLikeRatio": 0.12,
        "commentCount": 34,
        "likeCount": 282,
        "tgi": "男性向",
        "sourceNoteUrl": "https://www.xiaohongshu.com/explore/6a1f62c7000000002100b036",
        "topComments": [],
        "sampleNotes": [],
        "noteCount": 1,
        "analysis": "攻略/方法讨论 · 讨论质量轻度（评赞比0.12），轻度讨论信号",
        "suggestion": "围绕\"《女坦薇古丝95》稳上分攻略\"创作相关内容 · 讨论活跃(评论34) — 建议在话题热度消退前完成内容准备",
        "generatedAt": "2026-06-03T20:05:32.958949"
      }
    ],
    "blueOcean": [
      {
        "id": "bo1",
        "title": "当朋友突然约你七点上线吃鸡时",
        "game": "和平精英",
        "direction": "综合资讯",
        "likes": 310695,
        "comments": 5277,
        "avgSupply": 0,
        "supplyGap": true,
        "blueScore": 100,
        "sourceNoteUrl": "https://www.xiaohongshu.com/explore/68834926000000001d00f39c",
        "generatedAt": "2026-06-03T20:04:48.888855",
        "analysis": "[🔵 供给缺口] 当朋友突然约你七点上线吃鸡时 — 综合资讯方向的蓝海信号，内容供给极少，竞争小，建议尽快切入"
      },
      {
        "id": "bo2",
        "title": "不愧是地球online第二赛季老玩家",
        "game": "三角洲行动",
        "direction": "版本更新",
        "likes": 248069,
        "comments": 725,
        "avgSupply": 0,
        "supplyGap": true,
        "blueScore": 100,
        "sourceNoteUrl": "https://www.xiaohongshu.com/explore/6870ea350000000010010559",
        "generatedAt": "2026-06-03T20:04:54.151995",
        "analysis": "[🔵 供给缺口] 不愧是地球online第二赛季老玩家 — 版本更新方向的蓝海信号，内容供给极少，竞争小，建议尽快切入"
      },
      {
        "id": "bo3",
        "title": "我就没见过有正常的名字😂",
        "game": "英雄联盟",
        "direction": "综合资讯",
        "likes": 9780,
        "comments": 1633,
        "avgSupply": 0,
        "supplyGap": true,
        "blueScore": 100,
        "sourceNoteUrl": "https://www.xiaohongshu.com/explore/625a5cd5000000002103e7e4",
        "generatedAt": "2026-06-03T20:04:59.205834",
        "analysis": "[🔵 供给缺口] 我就没见过有正常的名字😂 — 综合资讯方向的蓝海信号，内容供给极少，竞争小，建议尽快切入"
      }
    ],
    "hotspots": [
      {
        "id": "h11",
        "title": "喵城之战",
        "game": "英雄联盟",
        "heatScore": 63,
        "cumulativeNotes": 1,
        "lifecycle": "萌芽期",
        "noteCount": 1,
        "likeCount": 3404,
        "commentCount": 225,
        "ageHours": 26.4,
        "analysis": "喵城之战 — 英雄联盟的话题内容，热度分63，互动数据表现优异",
        "noteUrl": "https://www.xiaohongshu.com/explore/6a1ea5aa000000000702137b",
        "generatedAt": "2026-06-03T20:04:49.805484",
        "noteDetails": []
      },
      {
        "id": "h2",
        "title": "我们的明天 感谢现役",
        "game": "王者荣耀",
        "heatScore": 61,
        "cumulativeNotes": 1,
        "lifecycle": "上升期",
        "noteCount": 1,
        "likeCount": 17857,
        "commentCount": 518,
        "ageHours": 6.8,
        "analysis": "我们的明天 感谢现役 — 王者荣耀的话题内容，热度分61，互动数据表现优异",
        "noteUrl": "https://www.xiaohongshu.com/explore/6a1fb82a000000003601b420",
        "generatedAt": "2026-06-03T20:04:39.959481",
        "noteDetails": []
      },
      {
        "id": "h10",
        "title": "一条蠕动的蛆",
        "game": "英雄联盟",
        "heatScore": 61,
        "cumulativeNotes": 1,
        "lifecycle": "萌芽期",
        "noteCount": 1,
        "likeCount": 3128,
        "commentCount": 262,
        "ageHours": 20.2,
        "analysis": "一条蠕动的蛆 — 英雄联盟的话题内容，热度分61，互动数据表现优异",
        "noteUrl": "https://www.xiaohongshu.com/explore/6a1efbfd000000000f03ac00",
        "generatedAt": "2026-06-03T20:04:49.805463",
        "noteDetails": []
      },
      {
        "id": "h6",
        "title": "对面好感值直接刷满",
        "game": "三角洲行动",
        "heatScore": 58,
        "cumulativeNotes": 1,
        "lifecycle": "萌芽期",
        "noteCount": 1,
        "likeCount": 3483,
        "commentCount": 76,
        "ageHours": 6.1,
        "analysis": "对面好感值直接刷满 — 三角洲行动的话题内容，热度分58，互动数据表现优异",
        "noteUrl": "https://www.xiaohongshu.com/explore/6a1ea9d2000000003701da5a",
        "generatedAt": "2026-06-03T20:04:46.473982",
        "noteDetails": []
      },
      {
        "id": "h14",
        "title": "你的使命 还没结束！！let’s goooooo",
        "game": "无畏契约",
        "heatScore": 58,
        "cumulativeNotes": 1,
        "lifecycle": "萌芽期",
        "noteCount": 1,
        "likeCount": 4026,
        "commentCount": 92,
        "ageHours": 21.6,
        "analysis": "你的使命 还没结束！！let’s goooooo — 无畏契约的话题内容，热度分58，互动数据表现优异",
        "noteUrl": "https://www.xiaohongshu.com/explore/6a1ee8930000000021023f47",
        "generatedAt": "2026-06-03T20:04:51.700968",
        "noteDetails": []
      },
      {
        "id": "h9",
        "title": "免费领小小拉克丝！铲铲最新活动！",
        "game": "金铲铲之战",
        "heatScore": 54,
        "cumulativeNotes": 1,
        "lifecycle": "萌芽期",
        "noteCount": 1,
        "likeCount": 2790,
        "commentCount": 137,
        "ageHours": 35.9,
        "analysis": "免费领小小拉克丝！铲铲最新活动！ — 金铲铲之战的话题内容，热度分54，互动数据表现优异",
        "noteUrl": "https://www.xiaohongshu.com/explore/6a1dcba3000000003502f2f0",
        "generatedAt": "2026-06-03T20:04:48.866304",
        "noteDetails": []
      },
      {
        "id": "h4",
        "title": "有人给你找密钥吗",
        "game": "和平精英",
        "heatScore": 52,
        "cumulativeNotes": 1,
        "lifecycle": "萌芽期",
        "noteCount": 1,
        "likeCount": 5192,
        "commentCount": 93,
        "ageHours": 27.4,
        "analysis": "有人给你找密钥吗 — 和平精英的话题内容，热度分52，互动数据表现优异",
        "noteUrl": "https://www.xiaohongshu.com/explore/6a1e965c000000000803fea8",
        "generatedAt": "2026-06-03T20:04:42.775689",
        "noteDetails": []
      },
      {
        "id": "h3",
        "title": "5款非常火的\"鹅仔AI皮肤码\"，各种角色都有!",
        "game": "和平精英",
        "heatScore": 51,
        "cumulativeNotes": 1,
        "lifecycle": "萌芽期",
        "noteCount": 1,
        "likeCount": 3741,
        "commentCount": 31,
        "ageHours": 13.2,
        "analysis": "5款非常火的\"鹅仔AI皮肤码\"，各种角色都有! — 和平精英的话题内容，热度分51，互动数据表现优异",
        "noteUrl": "https://www.xiaohongshu.com/explore/6a1f5ea40000000020039865",
        "generatedAt": "2026-06-03T20:04:42.775649",
        "noteDetails": []
      },
      {
        "id": "h7",
        "title": "我去，还有第二…3456关",
        "game": "三角洲行动",
        "heatScore": 51,
        "cumulativeNotes": 1,
        "lifecycle": "萌芽期",
        "noteCount": 1,
        "likeCount": 3730,
        "commentCount": 71,
        "ageHours": 21.4,
        "analysis": "我去，还有第二…3456关 — 三角洲行动的话题内容，热度分51，互动数据表现优异",
        "noteUrl": "https://www.xiaohongshu.com/explore/6a1eeac5000000003701d381",
        "generatedAt": "2026-06-03T20:04:46.474000",
        "noteDetails": []
      },
      {
        "id": "h18",
        "title": "卡通煎饼日常练习",
        "game": "火影忍者",
        "heatScore": 51,
        "cumulativeNotes": 1,
        "lifecycle": "上升期",
        "noteCount": 1,
        "likeCount": 10920,
        "commentCount": 123,
        "ageHours": 27.8,
        "analysis": "卡通煎饼日常练习 — 火影忍者的话题内容，热度分51，互动数据表现优异",
        "noteUrl": "https://www.xiaohongshu.com/explore/6a1e916c000000003502da27",
        "generatedAt": "2026-06-03T20:04:53.444787",
        "noteDetails": []
      },
      {
        "id": "h16",
        "title": "球赛转播画面竟然出现了火影！",
        "game": "火影忍者",
        "heatScore": 49,
        "cumulativeNotes": 1,
        "lifecycle": "萌芽期",
        "noteCount": 1,
        "likeCount": 2991,
        "commentCount": 205,
        "ageHours": 24.4,
        "analysis": "球赛转播画面竟然出现了火影！ — 火影忍者的话题内容，热度分49，互动数据表现优异",
        "noteUrl": "https://www.xiaohongshu.com/explore/6a1ec1b300000000360333b5",
        "generatedAt": "2026-06-03T20:04:53.444752",
        "noteDetails": []
      },
      {
        "id": "h21",
        "title": "医者执剑，柔亦有锋",
        "game": "永劫无间",
        "heatScore": 43,
        "cumulativeNotes": 1,
        "lifecycle": "萌芽期",
        "noteCount": 1,
        "likeCount": 2826,
        "commentCount": 19,
        "ageHours": 49.9,
        "analysis": "医者执剑，柔亦有锋 — 永劫无间的话题内容，热度分43，互动数据表现优异",
        "noteUrl": "https://www.xiaohongshu.com/explore/6a1c6c9f00000000380357b0",
        "generatedAt": "2026-06-03T20:04:56.848198",
        "noteDetails": []
      }
    ],
    "esports": [
      {
        "id": "e1",
        "topic": "AG超玩会 挑战者杯",
        "game": "王者荣耀",
        "tag": "挑战者杯",
        "heatScore": 46,
        "totalLikes": 4620,
        "noteCount": 1,
        "sampleNotes": [
          {
            "title": "成都AG超玩会·挑战者杯决赛晋级之路",
            "url": "https://www.xiaohongshu.com/explore/6a0fceb50000000006037154",
            "likes": 4620
          }
        ],
        "analysis": "AG超玩会 挑战者杯 — 王者荣耀赛事相关热点，值得关注社区讨论走向",
        "suggestion": "促产方向：赛事解读图文 / 精彩片段剪辑 / 选手故事",
        "generatedAt": "2026-06-03T20:04:43.290143"
      },
      {
        "id": "e2",
        "topic": "三角洲行动 职业联赛",
        "game": "三角洲行动",
        "tag": "烽火联赛",
        "heatScore": 45,
        "totalLikes": 718,
        "noteCount": 1,
        "sampleNotes": [
          {
            "title": "官宣！迈从×三角洲行动职业联赛正式合作",
            "url": "https://www.xiaohongshu.com/explore/694f4b0e000000002203ad1a",
            "likes": 718
          }
        ],
        "analysis": "三角洲行动 职业联赛 — 三角洲行动赛事相关热点，值得关注社区讨论走向",
        "suggestion": "促产方向：赛事解读图文 / 精彩片段剪辑 / 选手故事",
        "generatedAt": "2026-06-03T20:04:53.454233"
      }
    ]
  },
  "summary": {
    "discussionSprouts": 15,
    "blueOcean": 3,
    "hotspots": 12,
    "esports": 2,
    "totalGames": 11
  }
}