{
  "generatedAt": "2026-06-08T14:08:47.966578",
  "refreshInterval": "1h",
  "nextRefresh": "整点自动刷新",
  "boards": {
    "discussionSprouts": [
      {
        "id": "ds1",
        "title": "TI2026门票6月10日发售，优先购抢先购票！",
        "game": "DOTA2",
        "board": "discussion",
        "signalType": "讨论苗头",
        "commentToLikeRatio": 0.7,
        "commentCount": 326,
        "likeCount": 468,
        "tgi": "均衡",
        "sourceNoteUrl": "https://www.xiaohongshu.com/explore/6a151edb000000003601e350",
        "topComments": [],
        "sampleNotes": [],
        "noteCount": 1,
        "analysis": "社区热点讨论 · 讨论质量较高（评赞比0.7），评论区活跃度明显超过内容本身",
        "suggestion": "围绕\"TI2026门票6月10日发售，优先购抢\"创作相关内容 · 讨论活跃(评论326) — 建议在话题热度消退前完成内容准备",
        "generatedAt": "2026-06-08T14:08:47.966316"
      },
      {
        "id": "ds2",
        "title": "『回响//V26』局内展示",
        "game": "无畏契约",
        "board": "discussion",
        "signalType": "讨论苗头",
        "commentToLikeRatio": 0.6,
        "commentCount": 142,
        "likeCount": 238,
        "tgi": "均衡",
        "sourceNoteUrl": "https://www.xiaohongshu.com/explore/6a26473a000000002202740d",
        "topComments": [],
        "sampleNotes": [],
        "noteCount": 1,
        "analysis": "社区热点讨论 · 讨论质量较高（评赞比0.6），评论区活跃度明显超过内容本身",
        "suggestion": "围绕\"『回响//V26』局内展示\"创作相关内容 · 讨论活跃(评论142) — 建议在话题热度消退前完成内容准备",
        "generatedAt": "2026-06-08T14:08:47.966346"
      },
      {
        "id": "ds3",
        "title": "26年第12周TOP100手游流水排行!大盘止跌！",
        "game": "穿越火线：枪战王者",
        "board": "discussion",
        "signalType": "讨论苗头",
        "commentToLikeRatio": 0.42,
        "commentCount": 97,
        "likeCount": 229,
        "tgi": "均衡",
        "sourceNoteUrl": "https://www.xiaohongshu.com/explore/69c14ba100000000230276f7",
        "topComments": [],
        "sampleNotes": [],
        "noteCount": 1,
        "analysis": "排行/对比话题讨论 · 讨论质量中等偏上（评赞比0.42），潜在讨论信号",
        "suggestion": "围绕\"26年第12周TOP100手游流水排行!\"创作相关内容 · 讨论活跃(评论97) — 建议在话题热度消退前完成内容准备",
        "generatedAt": "2026-06-08T14:08:47.966364"
      },
      {
        "id": "ds4",
        "title": "比得过零氪最强轻狙M200-幻神吗？",
        "game": "穿越火线：枪战王者",
        "board": "discussion",
        "signalType": "讨论苗头",
        "commentToLikeRatio": 0.42,
        "commentCount": 95,
        "likeCount": 227,
        "tgi": "均衡",
        "sourceNoteUrl": "https://www.xiaohongshu.com/explore/69922233000000000c035c90",
        "topComments": [],
        "sampleNotes": [],
        "noteCount": 1,
        "analysis": "排行/对比话题讨论 · 讨论质量中等偏上（评赞比0.42），潜在讨论信号",
        "suggestion": "围绕\"比得过零氪最强轻狙M200-幻神吗？\"创作相关内容 · 讨论活跃(评论95) — 建议在话题热度消退前完成内容准备",
        "generatedAt": "2026-06-08T14:08:47.966379"
      },
      {
        "id": "ds5",
        "title": "无畏契约手游【归零者】CG首发",
        "game": "无畏契约",
        "board": "discussion",
        "signalType": "讨论苗头",
        "commentToLikeRatio": 0.41,
        "commentCount": 92,
        "likeCount": 223,
        "tgi": "均衡",
        "sourceNoteUrl": "https://www.xiaohongshu.com/explore/6a2134510000000008001754",
        "topComments": [],
        "sampleNotes": [],
        "noteCount": 1,
        "analysis": "社区热点讨论 · 讨论质量中等偏上（评赞比0.41），潜在讨论信号",
        "suggestion": "围绕\"无畏契约手游【归零者】CG首发\"创作相关内容 · 讨论活跃(评论92) — 建议在话题热度消退前完成内容准备",
        "generatedAt": "2026-06-08T14:08:47.966393"
      },
      {
        "id": "ds6",
        "title": "全新「裂变」赛季 6月26日正式开启！",
        "game": "三角洲行动",
        "board": "discussion",
        "signalType": "讨论苗头",
        "commentToLikeRatio": 0.36,
        "commentCount": 400,
        "likeCount": 1106,
        "tgi": "均衡",
        "sourceNoteUrl": "https://www.xiaohongshu.com/explore/6a2538e40000000008032960",
        "topComments": [],
        "sampleNotes": [],
        "noteCount": 1,
        "analysis": "版本更新讨论 · 讨论质量中等偏上（评赞比0.36），潜在讨论信号",
        "suggestion": "围绕\"全新「裂变」赛季 6月26日正式开启！\"创作相关内容 · 讨论活跃(评论400) — 建议在话题热度消退前完成内容准备",
        "generatedAt": "2026-06-08T14:08:47.966404"
      },
      {
        "id": "ds7",
        "title": "第一人称射击游戏排行榜前十名",
        "game": "穿越火线：枪战王者",
        "board": "discussion",
        "signalType": "讨论苗头",
        "commentToLikeRatio": 0.36,
        "commentCount": 377,
        "likeCount": 1049,
        "tgi": "男性向",
        "sourceNoteUrl": "https://www.xiaohongshu.com/explore/69c1209e00000000210061c6",
        "topComments": [],
        "sampleNotes": [],
        "noteCount": 1,
        "analysis": "排行/对比话题讨论 · 讨论质量中等偏上（评赞比0.36），潜在讨论信号",
        "suggestion": "围绕\"第一人称射击游戏排行榜前十名\"创作相关内容 · 讨论活跃(评论377) — 建议在话题热度消退前完成内容准备",
        "generatedAt": "2026-06-08T14:08:47.966417"
      },
      {
        "id": "ds8",
        "title": "新T0阵容5太空律动娜美（不卷莎妮拉）",
        "game": "金铲铲之战",
        "board": "discussion",
        "signalType": "讨论苗头",
        "commentToLikeRatio": 0.35,
        "commentCount": 113,
        "likeCount": 325,
        "tgi": "男性向",
        "sourceNoteUrl": "https://www.xiaohongshu.com/explore/6a2538270000000017029de2",
        "topComments": [],
        "sampleNotes": [],
        "noteCount": 1,
        "analysis": "版本更新讨论 · 讨论质量中等偏上（评赞比0.35），潜在讨论信号",
        "suggestion": "围绕\"新T0阵容5太空律动娜美（不卷莎妮拉）\"创作相关内容 · 讨论活跃(评论113) — 建议在话题热度消退前完成内容准备",
        "generatedAt": "2026-06-08T14:08:47.966434"
      },
      {
        "id": "ds9",
        "title": "上海TI直邀公告",
        "game": "DOTA2",
        "board": "discussion",
        "signalType": "讨论苗头",
        "commentToLikeRatio": 0.33,
        "commentCount": 231,
        "likeCount": 704,
        "tgi": "均衡",
        "sourceNoteUrl": "https://www.xiaohongshu.com/explore/6a15306b0000000038020604",
        "topComments": [],
        "sampleNotes": [],
        "noteCount": 1,
        "analysis": "版本更新讨论 · 讨论质量中等偏上（评赞比0.33），潜在讨论信号",
        "suggestion": "围绕\"上海TI直邀公告\"创作相关内容 · 讨论活跃(评论231) — 建议在话题热度消退前完成内容准备",
        "generatedAt": "2026-06-08T14:08:47.966447"
      },
      {
        "id": "ds10",
        "title": "恭喜小鸽子和rtz！",
        "game": "DOTA2",
        "board": "discussion",
        "signalType": "讨论苗头",
        "commentToLikeRatio": 0.32,
        "commentCount": 112,
        "likeCount": 354,
        "tgi": "均衡",
        "sourceNoteUrl": "https://www.xiaohongshu.com/explore/6a20f869000000002102274b",
        "topComments": [],
        "sampleNotes": [],
        "noteCount": 1,
        "analysis": "社区热点讨论 · 讨论质量中等偏上（评赞比0.32），潜在讨论信号",
        "suggestion": "围绕\"恭喜小鸽子和rtz！\"创作相关内容 · 讨论活跃(评论112) — 建议在话题热度消退前完成内容准备",
        "generatedAt": "2026-06-08T14:08:47.966459"
      },
      {
        "id": "ds11",
        "title": "要是高考可以选择海克斯",
        "game": "金铲铲之战",
        "board": "discussion",
        "signalType": "讨论苗头",
        "commentToLikeRatio": 0.25,
        "commentCount": 425,
        "likeCount": 1667,
        "tgi": "均衡",
        "sourceNoteUrl": "https://www.xiaohongshu.com/explore/6a2541e8000000003501e0a1",
        "topComments": [],
        "sampleNotes": [],
        "noteCount": 1,
        "analysis": "社区热点讨论 · 讨论质量中等（评赞比0.25），讨论正在发酵初期",
        "suggestion": "围绕\"要是高考可以选择海克斯\"创作相关内容 · 讨论活跃(评论425) — 建议在话题热度消退前完成内容准备",
        "generatedAt": "2026-06-08T14:08:47.966470"
      },
      {
        "id": "ds12",
        "title": "“拉克丝，我一定能找到完美时间线的！”",
        "game": "英雄联盟",
        "board": "discussion",
        "signalType": "讨论苗头",
        "commentToLikeRatio": 0.25,
        "commentCount": 107,
        "likeCount": 432,
        "tgi": "均衡",
        "sourceNoteUrl": "https://www.xiaohongshu.com/explore/6a258826000000002200be09",
        "topComments": [],
        "sampleNotes": [],
        "noteCount": 1,
        "analysis": "社区热点讨论 · 讨论质量中等（评赞比0.25），讨论正在发酵初期",
        "suggestion": "围绕\"“拉克丝，我一定能找到完美时间线的！”\"创作相关内容 · 讨论活跃(评论107) — 建议在话题热度消退前完成内容准备",
        "generatedAt": "2026-06-08T14:08:47.966482"
      },
      {
        "id": "ds13",
        "title": "以爱传声『回响//V26』6月11日（周四）上线",
        "game": "无畏契约",
        "board": "discussion",
        "signalType": "讨论苗头",
        "commentToLikeRatio": 0.25,
        "commentCount": 289,
        "likeCount": 1145,
        "tgi": "均衡",
        "sourceNoteUrl": "https://www.xiaohongshu.com/explore/6a263ffb0000000022025e79",
        "topComments": [],
        "sampleNotes": [],
        "noteCount": 1,
        "analysis": "版本更新讨论 · 讨论质量中等（评赞比0.25），讨论正在发酵初期",
        "suggestion": "围绕\"以爱传声『回响//V26』6月11日（周\"创作相关内容 · 讨论活跃(评论289) — 建议在话题热度消退前完成内容准备",
        "generatedAt": "2026-06-08T14:08:47.966494"
      },
      {
        "id": "ds14",
        "title": "donk和ame跨界合影",
        "game": "DOTA2",
        "board": "discussion",
        "signalType": "讨论苗头",
        "commentToLikeRatio": 0.23,
        "commentCount": 64,
        "likeCount": 273,
        "tgi": "均衡",
        "sourceNoteUrl": "https://www.xiaohongshu.com/explore/6a14b89e000000003501dcea",
        "topComments": [],
        "sampleNotes": [],
        "noteCount": 1,
        "analysis": "社区热点讨论 · 讨论质量中等（评赞比0.23），讨论正在发酵初期",
        "suggestion": "围绕\"donk和ame跨界合影\"创作相关内容 · 讨论活跃(评论64) — 建议在话题热度消退前完成内容准备",
        "generatedAt": "2026-06-08T14:08:47.966505"
      },
      {
        "id": "ds15",
        "title": "归零者套装6月11号上线手瓦，有史以来最好",
        "game": "无畏契约",
        "board": "discussion",
        "signalType": "讨论苗头",
        "commentToLikeRatio": 0.22,
        "commentCount": 63,
        "likeCount": 289,
        "tgi": "均衡",
        "sourceNoteUrl": "https://www.xiaohongshu.com/explore/6a25c2360000000022026736",
        "topComments": [],
        "sampleNotes": [],
        "noteCount": 1,
        "analysis": "版本更新讨论 · 讨论质量中等（评赞比0.22），讨论正在发酵初期",
        "suggestion": "围绕\"归零者套装6月11号上线手瓦，有史以来最\"创作相关内容 · 讨论活跃(评论63) — 建议在话题热度消退前完成内容准备",
        "generatedAt": "2026-06-08T14:08:47.966519"
      }
    ],
    "blueOcean": [
      {
        "id": "bo1",
        "title": "当朋友突然约你七点上线吃鸡时",
        "game": "和平精英",
        "direction": "综合资讯",
        "likes": 310693,
        "comments": 5276,
        "avgSupply": 0,
        "supplyGap": true,
        "blueScore": 100,
        "sourceNoteUrl": "https://www.xiaohongshu.com/explore/68834926000000001d00f39c",
        "generatedAt": "2026-06-08T14:08:00.507679",
        "analysis": "[🔵 供给缺口] 当朋友突然约你七点上线吃鸡时 — 综合资讯方向的蓝海信号，内容供给极少，竞争小，建议尽快切入"
      },
      {
        "id": "bo2",
        "title": "不愧是地球online第二赛季老玩家",
        "game": "三角洲行动",
        "direction": "版本更新",
        "likes": 248156,
        "comments": 725,
        "avgSupply": 0,
        "supplyGap": true,
        "blueScore": 100,
        "sourceNoteUrl": "https://www.xiaohongshu.com/explore/6870ea350000000010010559",
        "generatedAt": "2026-06-08T14:08:05.375546",
        "analysis": "[🔵 供给缺口] 不愧是地球online第二赛季老玩家 — 版本更新方向的蓝海信号，内容供给极少，竞争小，建议尽快切入"
      },
      {
        "id": "bo3",
        "title": "我就没见过有正常的名字😂",
        "game": "英雄联盟",
        "direction": "综合资讯",
        "likes": 9780,
        "comments": 1633,
        "avgSupply": 0,
        "supplyGap": true,
        "blueScore": 100,
        "sourceNoteUrl": "https://www.xiaohongshu.com/explore/625a5cd5000000002103e7e4",
        "generatedAt": "2026-06-08T14:08:11.455682",
        "analysis": "[🔵 供给缺口] 我就没见过有正常的名字😂 — 综合资讯方向的蓝海信号，内容供给极少，竞争小，建议尽快切入"
      }
    ],
    "hotspots": [
      {
        "id": "h2",
        "title": "【北京JDG王者荣耀分部人员变动公告】",
        "game": "王者荣耀",
        "heatScore": 74,
        "cumulativeNotes": 1,
        "lifecycle": "萌芽期",
        "noteCount": 1,
        "likeCount": 3417,
        "commentCount": 1112,
        "ageHours": 3.6,
        "analysis": "【北京JDG王者荣耀分部人员变动公告】 — 王者荣耀的话题内容，热度分74，互动数据表现优异",
        "noteUrl": "https://www.xiaohongshu.com/explore/6a25503200000000220244b3",
        "generatedAt": "2026-06-08T14:07:51.086898",
        "noteDetails": []
      },
      {
        "id": "h29",
        "title": "虽然吴邪还没被扒出来融的谁",
        "game": "永劫无间",
        "heatScore": 65,
        "cumulativeNotes": 1,
        "lifecycle": "萌芽期",
        "noteCount": 1,
        "likeCount": 6317,
        "commentCount": 720,
        "ageHours": 26.5,
        "analysis": "虽然吴邪还没被扒出来融的谁 — 永劫无间的话题内容，热度分65，互动数据表现优异",
        "noteUrl": "https://www.xiaohongshu.com/explore/6a24e7560000000022025abc",
        "generatedAt": "2026-06-08T14:08:07.527435",
        "noteDetails": []
      },
      {
        "id": "h17",
        "title": "哦嘛咧",
        "game": "英雄联盟",
        "heatScore": 61,
        "cumulativeNotes": 1,
        "lifecycle": "上升期",
        "noteCount": 1,
        "likeCount": 24342,
        "commentCount": 611,
        "ageHours": 50.6,
        "analysis": "哦嘛咧 — 英雄联盟的话题内容，热度分61，互动数据表现优异",
        "noteUrl": "https://www.xiaohongshu.com/explore/6a2394b9000000001702abaa",
        "generatedAt": "2026-06-08T14:08:00.190690",
        "noteDetails": []
      },
      {
        "id": "h19",
        "title": "祝Smoggy选手生日快乐🎂",
        "game": "无畏契约",
        "heatScore": 60,
        "cumulativeNotes": 1,
        "lifecycle": "萌芽期",
        "noteCount": 1,
        "likeCount": 4046,
        "commentCount": 811,
        "ageHours": 14.1,
        "analysis": "祝Smoggy选手生日快乐🎂 — 无畏契约的话题内容，热度分60，互动数据表现优异",
        "noteUrl": "https://www.xiaohongshu.com/explore/6a2562fd000000003502c403",
        "generatedAt": "2026-06-08T14:08:02.003789",
        "noteDetails": []
      },
      {
        "id": "h15",
        "title": "Faker这样的人做什么都会是标杆",
        "game": "英雄联盟",
        "heatScore": 57,
        "cumulativeNotes": 1,
        "lifecycle": "高峰期",
        "noteCount": 1,
        "likeCount": 73036,
        "commentCount": 557,
        "ageHours": 45.1,
        "analysis": "Faker这样的人做什么都会是标杆 — 英雄联盟的话题内容，热度分57，互动数据表现优异",
        "noteUrl": "https://www.xiaohongshu.com/explore/6a23e2ae000000001702f3a5",
        "generatedAt": "2026-06-08T14:08:00.190666",
        "noteDetails": []
      },
      {
        "id": "h3",
        "title": "刘邦叔叔祝大家旗开得胜～",
        "game": "王者荣耀",
        "heatScore": 54,
        "cumulativeNotes": 1,
        "lifecycle": "上升期",
        "noteCount": 1,
        "likeCount": 9450,
        "commentCount": 113,
        "ageHours": 4.0,
        "analysis": "刘邦叔叔祝大家旗开得胜～ — 王者荣耀的话题内容，热度分54，互动数据表现优异",
        "noteUrl": "https://www.xiaohongshu.com/explore/6a2624250000000022018df9",
        "generatedAt": "2026-06-08T14:07:51.086922",
        "noteDetails": []
      },
      {
        "id": "h7",
        "title": "这谁绷得住",
        "game": "和平精英",
        "heatScore": 53,
        "cumulativeNotes": 1,
        "lifecycle": "萌芽期",
        "noteCount": 1,
        "likeCount": 5791,
        "commentCount": 80,
        "ageHours": 22.1,
        "analysis": "这谁绷得住 — 和平精英的话题内容，热度分53，互动数据表现优异",
        "noteUrl": "https://www.xiaohongshu.com/explore/6a24bf7300000000350210df",
        "generatedAt": "2026-06-08T14:07:54.408586",
        "noteDetails": []
      },
      {
        "id": "h4",
        "title": "想要问问你敢不敢",
        "game": "王者荣耀",
        "heatScore": 52,
        "cumulativeNotes": 1,
        "lifecycle": "萌芽期",
        "noteCount": 1,
        "likeCount": 4744,
        "commentCount": 186,
        "ageHours": 4.4,
        "analysis": "想要问问你敢不敢 — 王者荣耀的话题内容，热度分52，互动数据表现优异",
        "noteUrl": "https://www.xiaohongshu.com/explore/6a261e950000000035028526",
        "generatedAt": "2026-06-08T14:07:51.086935",
        "noteDetails": []
      },
      {
        "id": "h8",
        "title": "假如我绷住了呢",
        "game": "和平精英",
        "heatScore": 52,
        "cumulativeNotes": 1,
        "lifecycle": "萌芽期",
        "noteCount": 1,
        "likeCount": 5877,
        "commentCount": 76,
        "ageHours": 25.6,
        "analysis": "假如我绷住了呢 — 和平精英的话题内容，热度分52，互动数据表现优异",
        "noteUrl": "https://www.xiaohongshu.com/explore/6a2446de0000000021021ab2",
        "generatedAt": "2026-06-08T14:07:54.408610",
        "noteDetails": []
      },
      {
        "id": "h24",
        "title": "三个人牵手果然就不怕了",
        "game": "火影忍者",
        "heatScore": 52,
        "cumulativeNotes": 1,
        "lifecycle": "上升期",
        "noteCount": 1,
        "likeCount": 10141,
        "commentCount": 80,
        "ageHours": 21.7,
        "analysis": "三个人牵手果然就不怕了 — 火影忍者的话题内容，热度分52，互动数据表现优异",
        "noteUrl": "https://www.xiaohongshu.com/explore/6a252a85000000003501ca20",
        "generatedAt": "2026-06-08T14:08:03.828252",
        "noteDetails": []
      },
      {
        "id": "h5",
        "title": "和平精英地铁逃生",
        "game": "和平精英",
        "heatScore": 51,
        "cumulativeNotes": 1,
        "lifecycle": "萌芽期",
        "noteCount": 1,
        "likeCount": 3956,
        "commentCount": 23,
        "ageHours": 18.6,
        "analysis": "和平精英地铁逃生 — 和平精英的话题内容，热度分51，互动数据表现优异",
        "noteUrl": "https://www.xiaohongshu.com/explore/6a2556d4000000000803e9d7",
        "generatedAt": "2026-06-08T14:07:54.408518",
        "noteDetails": []
      },
      {
        "id": "h13",
        "title": "入殓师好赖啊好赖啊",
        "game": "英雄联盟",
        "heatScore": 51,
        "cumulativeNotes": 1,
        "lifecycle": "萌芽期",
        "noteCount": 1,
        "likeCount": 3460,
        "commentCount": 78,
        "ageHours": 15.1,
        "analysis": "入殓师好赖啊好赖啊 — 英雄联盟的话题内容，热度分51，互动数据表现优异",
        "noteUrl": "https://www.xiaohongshu.com/explore/6a258860000000000602192e",
        "generatedAt": "2026-06-08T14:08:00.190632",
        "noteDetails": []
      }
    ],
    "esports": [
      {
        "id": "e1",
        "topic": "AG超玩会 挑战者杯",
        "game": "王者荣耀",
        "tag": "挑战者杯",
        "heatScore": 46,
        "totalLikes": 4648,
        "noteCount": 1,
        "sampleNotes": [
          {
            "title": "成都AG超玩会·挑战者杯决赛晋级之路",
            "url": "https://www.xiaohongshu.com/explore/6a0fceb50000000006037154",
            "likes": 4648
          }
        ],
        "analysis": "AG超玩会 挑战者杯 — 王者荣耀赛事相关热点，值得关注社区讨论走向",
        "suggestion": "促产方向：赛事解读图文 / 精彩片段剪辑 / 选手故事",
        "generatedAt": "2026-06-08T14:07:55.827842"
      },
      {
        "id": "e2",
        "topic": "三角洲行动 职业联赛",
        "game": "三角洲行动",
        "tag": "烽火联赛",
        "heatScore": 45,
        "totalLikes": 716,
        "noteCount": 1,
        "sampleNotes": [
          {
            "title": "官宣！迈从×三角洲行动职业联赛正式合作",
            "url": "https://www.xiaohongshu.com/explore/694f4b0e000000002203ad1a",
            "likes": 716
          }
        ],
        "analysis": "三角洲行动 职业联赛 — 三角洲行动赛事相关热点，值得关注社区讨论走向",
        "suggestion": "促产方向：赛事解读图文 / 精彩片段剪辑 / 选手故事",
        "generatedAt": "2026-06-08T14:08:05.252268"
      }
    ]
  },
  "summary": {
    "discussionSprouts": 15,
    "blueOcean": 3,
    "hotspots": 12,
    "esports": 2,
    "totalGames": 10
  }
}